flask_json.py
Flask_JSON-0.4.0.dist-info/LICENSE
Flask_JSON-0.4.0.dist-info/METADATA
Flask_JSON-0.4.0.dist-info/WHEEL
Flask_JSON-0.4.0.dist-info/top_level.txt
Flask_JSON-0.4.0.dist-info/RECORD
