Metadata-Version: 1.1
Name: Flask-JSON
Version: 0.4.0
Summary: Better JSON support for Flask
Home-page: https://github.com/skozlovf/flask-json
Author: Sergey Kozlov
Author-email: skozlovf@gmail.com
License: BSD
Platform: any
Classifier: Development Status :: 4 - Beta
Classifier: Environment :: Web Environment
Classifier: Framework :: Flask
Classifier: Intended Audience :: Developers
Classifier: License :: OSI Approved :: BSD License
Classifier: Operating System :: OS Independent
Classifier: Programming Language :: Python
Classifier: Programming Language :: Python :: 3
Classifier: Topic :: Internet :: WWW/HTTP :: Dynamic Content
Classifier: Topic :: Software Development :: Libraries :: Python Modules
